keyclock_dhruvanshu1775/__init__.py
keyclock_test_phase1/__init__.py
keyclock_test_phase1-0.0.3.dist-info/METADATA
keyclock_test_phase1-0.0.3.dist-info/WHEEL
keyclock_test_phase1-0.0.3.dist-info/top_level.txt
keyclock_test_phase1-0.0.3.dist-info/RECORD
